LICENSE
MANIFEST.in
README.rst
requirements.txt
setup.cfg
setup.py
aprsgate/__init__.py
aprsgate/classes.py
aprsgate/cmd.py
aprsgate/constants.py
aprsgate/functions.py
aprsgate/sat.py
aprsgate.egg-info/PKG-INFO
aprsgate.egg-info/SOURCES.txt
aprsgate.egg-info/dependency_links.txt
aprsgate.egg-info/entry_points.txt
aprsgate.egg-info/not-zip-safe
aprsgate.egg-info/pbr.json
aprsgate.egg-info/requires.txt
aprsgate.egg-info/top_level.txt