Metadata-Version: 1.1
Name: aprsgate
Version: 1.0.0
Summary: Python APRS Gateway.
Home-page: https://github.com/ampledata/aprsgate
Author: Greg Albrecht
Author-email: oss@undef.net
License: Copyright 2016 Orion Labs, Inc.
